fastsession/__init__.py
fastsession/fast_session_middleware.py
fastsession/memory_store.py
fastsession/timed_signature_serializer.py
fastsession-0.3.0.dist-info/LICENSE
fastsession-0.3.0.dist-info/METADATA
fastsession-0.3.0.dist-info/WHEEL
fastsession-0.3.0.dist-info/top_level.txt
fastsession-0.3.0.dist-info/RECORD
