Metadata-Version: 2.1
Name: fastsession
Version: 0.3.0
Summary: A session middleware for Starlette and FastAPI
Home-page: https://github.com/riversun/FastSession
Author: Tom Misawa
Author-email: riversun.org@gmail.com
Classifier: Development Status :: 3 - Alpha
Classifier: Intended Audience :: Developers
Classifier: License :: OSI Approved :: Apache Software License
Classifier: Programming Language :: Python :: 3.8
Classifier: Programming Language :: Python :: 3.9
Classifier: Programming Language :: Python :: 3.10
Requires-Python: >=3.8
License-File: LICENSE
